{
  "response": {
    "numFound": 572088,
    "start": 0,
    "maxScore": 0.5001635,
    "docs": [
      {
        "id": "a64274ac-6835-3e3d-351a-68a8414fb06a",
        "file_id": "a64274ac-6835-3e3d-351a-68a8414fb06a",
        "file_name": "KKDY MISSOURI STANDS UNITED 0719-0729 (2)",
        "file_extension": "pdf",
        "file_size": 167472,
        "file_status": "com_cpy",
        "folder_id": "a5f3a9be-99c0-e6bc-c5a4-f84c038e534a",
        "create_ts": "2022-07-20T19:19:54.595Z",
        "last_update_ts": "2022-07-20T19:20:51.515Z",
        "active_ind": "Y",
        "file_manager_id": "a4088dd4-b214-4261-b1d2-5bc30789a724",
        "file_folder_path": "Political Files/2022/Non-Candidate Issue Ads",
        "full_qualified_file_name": "Political Files/2022/Non-Candidate Issue Ads/KKDY MISSOURI STANDS UNITED 0719-0729 (2)",
        "entity_id": "39544",
        "source_service_code": "FM",
        "callsign": "KKDY",
        "political_file_type": "NCIA",
        "campaign_year": "2022",
        "_version_": 1738900551716831200,
        "score": 0.24995676
      },
      {
        "id": "6bccf2e9-3991-949d-13bc-f0f0d0611078",
        "file_id": "6bccf2e9-3991-949d-13bc-f0f0d0611078",
        "file_name": "KSPQ MISSOURI STANDS UNITED 0719-0729 ",
        "file_extension": "pdf",
        "file_size": 1720626,
        "file_status": "com_cpy",
        "folder_id": "f8444e47-ecd2-93d1-1edc-275d44768b39",
        "create_ts": "2022-07-20T19:18:56.195Z",
        "last_update_ts": "2022-07-20T19:18:36.773Z",
        "active_ind": "Y",
        "file_manager_id": "de185ecd-99c8-45cf-aa75-e4176ca9a692",
        "file_folder_path": "Political Files/2022/Non-Candidate Issue Ads",
        "full_qualified_file_name": "Political Files/2022/Non-Candidate Issue Ads/KSPQ MISSOURI STANDS UNITED 0719-0729 ",
        "entity_id": "47951",
        "source_service_code": "FM",
        "callsign": "KSPQ",
        "political_file_type": "NCIA",
        "campaign_year": "2022",
        "_version_": 1738900490753671200,
        "score": 0.24995676
      },
      {
        "id": "fba73d5b-c691-afbb-1c16-baeae8763b9b",
        "file_id": "fba73d5b-c691-afbb-1c16-baeae8763b9b",
        "file_name": "TEAM JUSTIN BROWN WK 0718-0724",
        "file_extension": "pdf",
        "file_size": 1152912,
        "file_status": "com_cpy",
        "folder_id": "213ff88b-00c6-db96-25db-583cda35a9d2",
        "create_ts": "2022-07-20T19:18:11.88Z",
        "last_update_ts": "2022-07-20T19:17:52.467Z",
        "active_ind": "Y",
        "file_manager_id": "71cc9d0d-0a76-4a9f-8433-e91d710f8cba",
        "file_folder_path": "Political Files/2022/State",
        "full_qualified_file_name": "Political Files/2022/State/TEAM JUSTIN BROWN WK 0718-0724",
        "entity_id": "50349",
        "source_service_code": "FM",
        "callsign": "KUKU-FM",
        "political_file_type": "PA",
        "office_type": "State",
        "campaign_year": "2022",
        "_version_": 1738900444296511500,
        "score": 0.24995676
      },
      {
        "id": "a690d0f5-17df-74fb-90ee-47b9fca562a3",
        "file_id": "a690d0f5-17df-74fb-90ee-47b9fca562a3",
        "file_name": "WNAC_Seth Magaziner_Congress_RI_Dem_3632447_08.30- 09.05.22",
        "file_extension": "pdf",
        "file_size": 268250,
        "file_status": "com_cpy",
        "folder_id": "90699b6a-eeef-3fa2-ed80-e304b5662d78",
        "create_ts": "2022-07-20T19:18:00.838Z",
        "last_update_ts": "2022-07-20T19:17:41.372Z",
        "active_ind": "Y",
        "file_manager_id": "ffcdb39e-4c73-4440-b562-658657765e78",
        "file_folder_path": "Political Files/2022/Federal/US House/WNAC Seth Magaziner Congress RI DEM",
        "full_qualified_file_name": "Political Files/2022/Federal/US House/WNAC Seth Magaziner Congress RI DEM/WNAC_Seth Magaziner_Congress_RI_Dem_3632447_08.30- 09.05.22",
        "entity_id": "73311",
        "source_service_code": "TV",
        "network_affiliation": "FOX",
        "nielsen_dma_rank": "PROVIDENCE-NEW BEDFORD",
        "callsign": "WNAC-TV",
        "political_file_type": "PA",
        "office_type": "US House",
        "campaign_year": "2022",
        "_version_": 1738900432661512200,
        "score": 0.24995676
      },
      {
        "id": "a4349656-e841-5450-8657-a11028be7115",
        "file_id": "a4349656-e841-5450-8657-a11028be7115",
        "file_name": "WNAC_Seth Magaziner_Congress_RI_Dem_3631998_08.23- 08.29.22",
        "file_extension": "pdf",
        "file_size": 245769,
        "file_status": "com_cpy",
        "folder_id": "90699b6a-eeef-3fa2-ed80-e304b5662d78",
        "create_ts": "2022-07-20T19:18:00.838Z",
        "last_update_ts": "2022-07-20T19:17:41.349Z",
        "active_ind": "Y",
        "file_manager_id": "7d105123-5f2f-462a-8a33-1625c64e7de1",
        "file_folder_path": "Political Files/2022/Federal/US House/WNAC Seth Magaziner Congress RI DEM",
        "full_qualified_file_name": "Political Files/2022/Federal/US House/WNAC Seth Magaziner Congress RI DEM/WNAC_Seth Magaziner_Congress_RI_Dem_3631998_08.23- 08.29.22",
        "entity_id": "73311",
        "source_service_code": "TV",
        "network_affiliation": "FOX",
        "nielsen_dma_rank": "PROVIDENCE-NEW BEDFORD",
        "callsign": "WNAC-TV",
        "political_file_type": "PA",
        "office_type": "US House",
        "campaign_year": "2022",
        "_version_": 1738900432641589200,
        "score": 0.24995676
      },
      {
        "id": "0625a946-f874-ab70-6051-f58dd0e30ce0",
        "file_id": "0625a946-f874-ab70-6051-f58dd0e30ce0",
        "file_name": "WNAC_Seth Magaziner_Congress_RI_Dem_36232987_09.06- 09.12.22",
        "file_extension": "pdf",
        "file_size": 286421,
        "file_status": "com_cpy",
        "folder_id": "90699b6a-eeef-3fa2-ed80-e304b5662d78",
        "create_ts": "2022-07-20T19:18:00.84Z",
        "last_update_ts": "2022-07-20T19:17:41.278Z",
        "active_ind": "Y",
        "file_manager_id": "19c9fdeb-8e65-4188-820f-734dfc3647ab",
        "file_folder_path": "Political Files/2022/Federal/US House/WNAC Seth Magaziner Congress RI DEM",
        "full_qualified_file_name": "Political Files/2022/Federal/US House/WNAC Seth Magaziner Congress RI DEM/WNAC_Seth Magaziner_Congress_RI_Dem_36232987_09.06- 09.12.22",
        "entity_id": "73311",
        "source_service_code": "TV",
        "network_affiliation": "FOX",
        "nielsen_dma_rank": "PROVIDENCE-NEW BEDFORD",
        "callsign": "WNAC-TV",
        "political_file_type": "PA",
        "office_type": "US House",
        "campaign_year": "2022",
        "_version_": 1738900432562946000,
        "score": 0.24995676
      },
      {
        "id": "8ea52bc3-061b-ff8a-4ad3-ef597bd0bcb9",
        "file_id": "8ea52bc3-061b-ff8a-4ad3-ef597bd0bcb9",
        "file_name": "WNAC_Seth Magaziner_Congress_RI_Dem_3631985_08.16- 08.22.22",
        "file_extension": "pdf",
        "file_size": 225857,
        "file_status": "com_cpy",
        "folder_id": "90699b6a-eeef-3fa2-ed80-e304b5662d78",
        "create_ts": "2022-07-20T19:18:00.762Z",
        "last_update_ts": "2022-07-20T19:17:41.084Z",
        "active_ind": "Y",
        "file_manager_id": "404c88fa-6c30-43fc-b3f5-5aa3a0c46c59",
        "file_folder_path": "Political Files/2022/Federal/US House/WNAC Seth Magaziner Congress RI DEM",
        "full_qualified_file_name": "Political Files/2022/Federal/US House/WNAC Seth Magaziner Congress RI DEM/WNAC_Seth Magaziner_Congress_RI_Dem_3631985_08.16- 08.22.22",
        "entity_id": "73311",
        "source_service_code": "TV",
        "network_affiliation": "FOX",
        "nielsen_dma_rank": "PROVIDENCE-NEW BEDFORD",
        "callsign": "WNAC-TV",
        "political_file_type": "PA",
        "office_type": "US House",
        "campaign_year": "2022",
        "_version_": 1738900432361619500,
        "score": 0.24995676
      },
      {
        "id": "f4c19047-3a34-340c-5798-a22bb06c50dd",
        "file_id": "f4c19047-3a34-340c-5798-a22bb06c50dd",
        "file_name": "EXYZ Sharon-McPhail-for-Congress-Political-PFD-07-18-2022 Supplement",
        "file_extension": "pdf",
        "file_size": 61816,
        "file_status": "com_cpy",
        "folder_id": "283090ac-6cdb-d69a-34a9-4d210b3f6af2",
        "create_ts": "2022-07-20T19:09:01.147Z",
        "last_update_ts": "2022-07-20T19:09:57.929Z",
        "active_ind": "Y",
        "file_manager_id": "4b7af1e0-a017-4dab-9345-8202bdb73bf3",
        "file_folder_path": "Political Files/2022/Federal/US House/WXYZ D2/Sharon McPhail Democrat/Political Disclosure",
        "full_qualified_file_name": "Political Files/2022/Federal/US House/WXYZ D2/Sharon McPhail Democrat/Political Disclosure/EXYZ Sharon-McPhail-for-Congress-Political-PFD-07-18-2022 Supplement",
        "entity_id": "10267",
        "source_service_code": "TV",
        "network_affiliation": "ABC",
        "nielsen_dma_rank": "DETROIT",
        "callsign": "WXYZ-TV",
        "political_file_type": "PA",
        "office_type": "US House",
        "campaign_year": "2022",
        "_version_": 1738899866397966300,
        "score": 0.24995676
      },
      {
        "id": "f0140512-14df-d138-6023-c1b03c3c2b67",
        "file_id": "f0140512-14df-d138-6023-c1b03c3c2b67",
        "file_name": "COALITION FOR SAFE, RESPONSIBLE GAMING 06.27.22-07.17.22 2291006-1",
        "file_extension": "pdf",
        "file_size": 482381,
        "file_status": "com_cpy",
        "folder_id": "61216577-7aed-a6a1-c5fd-ccd04679c668",
        "create_ts": "2022-07-20T19:06:29.178Z",
        "last_update_ts": "2022-07-20T19:07:26.29Z",
        "active_ind": "Y",
        "file_manager_id": "6d0a6def-d7d6-4e2a-bd11-631c24c99e8d",
        "file_folder_path": "Political Files/2022/Non-Candidate Issue Ads/COALITION FOR SAFE AND RESPONSIBLE GAMING",
        "full_qualified_file_name": "Political Files/2022/Non-Candidate Issue Ads/COALITION FOR SAFE AND RESPONSIBLE GAMING/COALITION FOR SAFE, RESPONSIBLE GAMING 06.27.22-07.17.22 2291006-1",
        "entity_id": "33875",
        "source_service_code": "TV",
        "network_affiliation": "NBC",
        "nielsen_dma_rank": "SACRAMNTO-STKTON-MODESTO",
        "callsign": "KCRA-TV",
        "political_file_type": "NCIA",
        "campaign_year": "2022",
        "_version_": 1738899707400290300,
        "score": 0.24995676
      },
      {
        "id": "4521058e-684b-0042-cd1c-4c7adeea45ac",
        "file_id": "4521058e-684b-0042-cd1c-4c7adeea45ac",
        "file_name": "Bennet-for-Colorado-Political-PFD-07-20-2022",
        "file_extension": "pdf",
        "file_size": 51138,
        "file_status": "com_cpy",
        "folder_id": "35c4f372-7afe-af40-b0d6-9efea265fd95",
        "create_ts": "2022-07-20T19:05:23.847Z",
        "last_update_ts": "2022-07-20T19:06:20.684Z",
        "active_ind": "Y",
        "file_manager_id": "3a393451-093e-41c2-8117-3f9f9ed80fb4",
        "file_folder_path": "Political Files/2022/Federal/US Senate/Bennet",
        "full_qualified_file_name": "Political Files/2022/Federal/US Senate/Bennet/Bennet-for-Colorado-Political-PFD-07-20-2022",
        "entity_id": "59014",
        "source_service_code": "TV",
        "network_affiliation": "NBC",
        "nielsen_dma_rank": "COLORADO SPRINGS-PUEBLO",
        "callsign": "KOAA-TV",
        "political_file_type": "PA",
        "office_type": "US Senate",
        "campaign_year": "2022",
        "_version_": 1738899638606364700,
        "score": 0.24995676
      }
    ],
    "facets": {
      "nielsen_dma_rank": {
        "DES MOINES-AMES": 8389,
        "WILKES BARRE-SCRANTON": 7830,
        "LAS VEGAS": 7672,
        "CEDAR RAPIDS-WTRLO-IWC&DUB": 7225,
        "PITTSBURGH": 7203,
        "WEST PALM BEACH-FT. PIERCE": 5889,
        "HONOLULU": 5239,
        "DULUTH-SUPERIOR": 4659,
        "CHARLESTON-HUNTINGTON": 4401,
        "PORTLAND-AUBURN": 4336,
        "TALLAHASSEE-THOMASVILLE": 4217,
        "OMAHA": 4089,
        "RALEIGH-DURHAM (FAYETVLLE)": 3989,
        "BUTTE-BOZEMAN": 3664,
        "PORTLAND OR": 3569,
        "EUGENE": 3518,
        "MISSOULA": 3485,
        "MINNEAPOLIS-ST. PAUL": 3286,
        "CHAMPAIGN&SPRNGFLD-DECATUR": 3247,
        "BEND OR": 3245,
        "SACRAMNTO-STKTON-MODESTO": 3101,
        "FRESNO-VISALIA": 3080,
        "CHICAGO": 3066,
        "WAUSAU-RHINELANDER": 3049,
        "SAVANNAH": 2933,
        "BIRMINGHAM (ANN TUSC)": 2793,
        "QUINCY-HANNIBAL-KEOKUK": 2791,
        "KANSAS CITY": 2781,
        "FT. WAYNE": 2730,
        "MILWAUKEE": 2660,
        "GREENSBORO-H.POINT-W.SALEM": 2561,
        "PEORIA-BLOOMINGTON": 2548,
        "Greenville-Spartanburg-Asheville-Anderson": 2354,
        "PHILADELPHIA": 2339,
        "ROCKFORD": 2202,
        "TAMPA-ST. PETE (SARASOTA)": 2201,
        "GRAND RAPIDS-KALMZOO-B.CRK": 2199,
        "LA CROSSE-EAU CLAIRE": 2180,
        "WASHINGTON DC (HAGRSTWN)": 2028,
        "MADISON": 2004,
        "ROCHESTR-MASON CITY-AUSTIN": 2003,
        "ALBUQUERQUE-SANTA FE": 1962,
        "GREAT FALLS": 1947,
        "LEXINGTON": 1941,
        "BLUEFIELD-BECKLEY-OAK HILL": 1763,
        "SIOUX CITY": 1754,
        "PADUCAH-CAPE GIRARD-HARSBG": 1682,
        "LINCOLN & HASTINGS-KRNY": 1668,
        "PHOENIX (PRESCOTT)": 1649,
        "BURLINGTON-PLATTSBURGH": 1648,
        "BINGHAMTON": 1617,
        "GREENVLL-SPART-ASHEVLL-AND": 1559,
        "PROVIDENCE-NEW BEDFORD": 1495,
        "FARGO-VALLEY CITY": 1455,
        "LITTLE ROCK-PINE BLUFF": 1452,
        "GREEN BAY-APPLETON": 1421,
        "CHATTANOOGA": 1381,
        "MINOT-BISMARCK-DICKINSON": 1371,
        "ST. LOUIS": 1313,
        "MIAMI-FT. LAUDERDALE": 1308,
        "ANCHORAGE": 1300,
        "WICHITA-HUTCHINSON PLUS": 1292,
        "GAINESVILLE": 1268,
        "LOS ANGELES": 1232,
        "JOHNSTOWN-ALTOONA-ST COLGE": 1231,
        "LOUISVILLE": 1191,
        "NEW YORK": 1142,
        "COLUMBUS OH": 1114,
        "CHARLOTTE": 1112,
        "SALT LAKE CITY": 1111,
        "GLENDIVE": 1081,
        "DENVER": 1066,
        "FT. SMITH-FAY-SPRNGDL-RGRS": 1065,
        "ORLANDO-DAYTONA BCH-MELBRN": 1048,
        "DAYTON": 1003,
        "JACKSON MS": 1003,
        "OKLAHOMA CITY": 973,
        "DALLAS-FT. WORTH": 927,
        "TULSA": 912,
        "PANAMA CITY": 888,
        "LANSING": 878,
        "INDIANAPOLIS": 845,
        "YOUNGSTOWN": 822,
        "GREENVILLE-N.BERN-WASHNGTN": 805,
        "HELENA": 798,
        "MACON": 779,
        "FLINT-SAGINAW-BAY CITY": 768,
        "COLORADO SPRINGS-PUEBLO": 762,
        "TWIN FALLS": 757,
        "AUSTIN": 742,
        "ATLANTA": 726,
        "RENO": 716,
        "BUFFALO": 704,
        "SAN FRANCISCO-OAK-SAN JOSE": 694,
        "BANGOR": 676,
        "TUCSON (SIERRA VISTA)": 673,
        "HARTFORD & NEW HAVEN": 671,
        "MONTEREY-SALINAS": 668,
        "SAN DIEGO": 659,
        "EL PASO (LAS CRUCES)": 642
      },
      "network_affiliation": {
        "ABC": 65050,
        "NBC": 61351,
        "CBS": 42899,
        "FOX": 30667,
        "PBS": 15171,
        "CW": 12467,
        "IND": 3051,
        "MYTV": 2280,
        "UNIVISION": 1961,
        "MY NETWORK": 1686,
        "CBS/NBC": 1081,
        "FAMILYNET": 1035,
        "MNT": 958,
        "ION": 939,
        "TELEMUNDO": 937,
        "N/A": 655,
        "CBS/CW": 613,
        "UNIMAS": 610,
        "INDEPENDENT": 435,
        "NBC & CBS": 376,
        "THE CW NETWORK": 342,
        "MYNETWORKTV": 317,
        "ABC, NBC": 236,
        "NONE": 233,
        "ETV": 218,
        "TRINITY BROADCASTING NETWORK": 185,
        "NBC & CW (DIGITAL ONLY)": 162,
        "Independent": 158,
        "MeTV": 136,
        "CBS AND CW": 100,
        "CBS AND FOX": 95,
        "CBS/FOX": 95,
        "NBC/CW": 95,
        "THIS NETWORK LLC": 94,
        "MY NETWORK TV": 77,
        "CW TELEVISION NETWORK": 50,
        "TBN": 46,
        "AZTECA AMERICA": 40,
        "CW/MeTV": 35,
        "MYNETWORK TV": 30,
        "MTV TR3S": 28,
        "ABC; NBC": 27,
        "ABC & CW (DIGITAL ONLY)": 21,
        "AMER1 (CH 44-1); AZTECA AMERICA (CH. 44-2)": 19,
        "PUBLIC BROADCASTING SERVICE": 15,
        "MNT AND CW (DIGITAL ONLY)": 12,
        "Cablevision": 10,
        "RTN": 9,
        "NBC/FOX": 8,
        "TELMUNDO": 8,
        "UNVISION": 8,
        "iON": 6,
        "My Net, MeTV, Movies Network": 4,
        "SBS/MEGA": 4,
        "TBN ENLACE": 4,
        "CW, AMERICA ONE": 3,
        "MYNETWORK": 3,
        "REL": 3,
        "SHOP AT HM": 3,
        "TUVISION": 1
      },
      "campaign_year": {
        "2012": 3181,
        "2013": 384,
        "2014": 22060,
        "2015": 6067,
        "2016": 66093,
        "2017": 10303,
        "2018": 67565,
        "2019": 13891,
        "2020": 124113,
        "2021": 22739,
        "2022": 52830,
        "KYAZ": 5,
        "Fede": 1
      },
      "office_type": {
        "State": 82969,
        "US Senate": 53815,
        "US House": 47231,
        "Presidential": 37877,
        "Local": 28416
      },
      "non_political_file_folder": {
        "Records Concerning Commercial Limits in Childrens Programs": 63709,
        "Issues and Programs Lists": 47687,
        "Equal Employment Opportunity Records": 37669,
        "Donor Lists - Applicable Only for NCEs": 12462,
        "FCC Authorizations": 7524,
        "Local Public Notice Announcements": 1890,
        "Availability of Signals": 1875,
        "Applications and Related Materials": 1720,
        "FCC Investigations or Complaints": 1557,
        "Must-Carry or Retransmission Consent": 1300,
        "Childrens TV Programming Reports": 1161,
        "Ownership Reports": 1152,
        "Class A TV Continuing Eligibility": 668,
        "Political Matters and Controversial Issues Disclosures": 667,
        "State and Local Franchising Related Materials": 503,
        "Time Brokerage Agreements": 457,
        "Channels Delivered": 275,
        "Compatibility with Consumer Electronics Equipment": 148,
        "Information on Third-Party Fundraising - For NCE Stations Only": 85,
        "Auction Transition Consumer Certification": 83,
        "Joint Sales Agreements": 79,
        "Citizen Agreements": 57,
        "Shared Service Agreements": 52,
        "Operator Interests in Video Programming": 33,
        "Sponsorship Identification": 16,
        "Leased Access": 14,
        "Foreign Government-Provided Programming Disclosures": 4,
        "Noncommercial Set-Aside": 1
      },
      "source_service_code": {
        "TV": 259302,
        "CABLE": 133874,
        "FM": 124199,
        "AM": 48069,
        "DBS": 6644
      },
      "political_file_type": {
        "PA": 252161,
        "NCIA": 137079
      }
    }
  },
  "request": {
    "qs": "t=opif&q=page%20offset%200&s=0&o=new",
    "query": {
      "t": "opif",
      "q": "page offset 0",
      "s": "0",
      "o": "new"
    }
  },
  "responseStatus": {
    "status": 200,
    "type": "OK",
    "queryTime": 1946,
    "processTime": 957,
    "responseTime": 1957
  }
}
