{
  "response": {
    "numFound": 565085,
    "start": 0,
    "maxScore": 0.5001635,
    "docs": [
      {
        "id": "15e64a13-ff94-6a68-6ec7-779f39a4d766",
        "file_id": "15e64a13-ff94-6a68-6ec7-779f39a4d766",
        "file_name": "radio nab Chuck Gray 07022022-07092022 signed",
        "file_extension": "pdf",
        "file_size": 1108373,
        "file_status": "com_cpy",
        "folder_id": "479cd835-11fb-a466-1ccd-80ba2041e0b8",
        "create_ts": "2022-07-04T04:17:08.143Z",
        "last_update_ts": "2022-07-04T04:17:25.071Z",
        "active_ind": "Y",
        "file_manager_id": "37ebd9a5-a76f-44e7-8e35-03b68f487c86",
        "file_folder_path": "Political Files/2022/State",
        "full_qualified_file_name": "Political Files/2022/State/radio nab Chuck Gray 07022022-07092022 signed",
        "entity_id": "35861",
        "source_service_code": "AM",
        "callsign": "KVOC",
        "political_file_type": "PA",
        "office_type": "State",
        "campaign_year": "2022",
        "_version_": 1737394202902265900,
        "score": 0.24995676
      },
      {
        "id": "35da1857-ffde-ec69-aea4-e02e5324dffd",
        "file_id": "35da1857-ffde-ec69-aea4-e02e5324dffd",
        "file_name": "radio nab Chuck Gray 07022022-07092022 signed",
        "file_extension": "pdf",
        "file_size": 1108373,
        "file_status": "com_cpy",
        "folder_id": "8b0e032f-c650-b502-84a0-f4f1bed4b5dd",
        "create_ts": "2022-07-04T04:15:17.868Z",
        "last_update_ts": "2022-07-04T04:15:19.515Z",
        "active_ind": "Y",
        "file_manager_id": "a46b3a10-cef9-45ba-a4e4-dbeb29bb4fc6",
        "file_folder_path": "Political Files/2022/State",
        "full_qualified_file_name": "Political Files/2022/State/radio nab Chuck Gray 07022022-07092022 signed",
        "entity_id": "11927",
        "source_service_code": "FM",
        "callsign": "KMLD",
        "political_file_type": "PA",
        "office_type": "State",
        "campaign_year": "2022",
        "_version_": 1737394087385890800,
        "score": 0.24995676
      },
      {
        "id": "70fd8500-c5ea-d37a-1316-355b1f1152e3",
        "file_id": "70fd8500-c5ea-d37a-1316-355b1f1152e3",
        "file_name": "radio nab Chuck Gray 07022022-07092022 signed",
        "file_extension": "pdf",
        "file_size": 1108373,
        "file_status": "com_cpy",
        "folder_id": "330ba30e-e9f0-0a8b-5b86-7d2c1dfae11a",
        "create_ts": "2022-07-04T04:09:52.552Z",
        "last_update_ts": "2022-07-04T04:09:37.861Z",
        "active_ind": "Y",
        "file_manager_id": "31d6b36e-423f-4084-aa6b-e089429b41da",
        "file_folder_path": "Political Files/2022/State",
        "full_qualified_file_name": "Political Files/2022/State/radio nab Chuck Gray 07022022-07092022 signed",
        "entity_id": "15925",
        "source_service_code": "FM",
        "callsign": "KHOC",
        "political_file_type": "PA",
        "office_type": "State",
        "campaign_year": "2022",
        "_version_": 1737393746160386000,
        "score": 0.24995676
      },
      {
        "id": "50ae5294-d2cc-5e13-4ed2-a14c0f97be82",
        "file_id": "50ae5294-d2cc-5e13-4ed2-a14c0f97be82",
        "file_name": "radio nab Chuck Gray 07022022-07092022 signed",
        "file_extension": "pdf",
        "file_size": 1108373,
        "file_status": "com_cpy",
        "folder_id": "33ba78f4-d9a6-b46d-ed38-e5cfa7604dc8",
        "create_ts": "2022-07-04T04:08:43.402Z",
        "last_update_ts": "2022-07-04T04:09:00.383Z",
        "active_ind": "Y",
        "file_manager_id": "7f189b51-7c03-4661-b118-dce704e845fb",
        "file_folder_path": "Political Files/2022/State",
        "full_qualified_file_name": "Political Files/2022/State/radio nab Chuck Gray 07022022-07092022 signed",
        "entity_id": "47878",
        "source_service_code": "FM",
        "callsign": "KQLT",
        "political_file_type": "PA",
        "office_type": "State",
        "campaign_year": "2022",
        "_version_": 1737393673712173000,
        "score": 0.24995676
      },
      {
        "id": "6d0b2533-047c-8040-fd09-0e2b8982476d",
        "file_id": "6d0b2533-047c-8040-fd09-0e2b8982476d",
        "file_name": "radio nab Chuck Gray 07022022-07092022 signed",
        "file_extension": "pdf",
        "file_size": 1108373,
        "file_status": "com_cpy",
        "folder_id": "1f414add-5b55-47b3-601d-c149e6032d5e",
        "create_ts": "2022-07-04T04:07:27.542Z",
        "last_update_ts": "2022-07-04T04:07:12.865Z",
        "active_ind": "Y",
        "file_manager_id": "73fbec25-fe20-4fed-9e5a-a37c0427e97d",
        "file_folder_path": "Political Files/2022/State",
        "full_qualified_file_name": "Political Files/2022/State/radio nab Chuck Gray 07022022-07092022 signed",
        "entity_id": "43477",
        "source_service_code": "FM",
        "callsign": "KASS",
        "political_file_type": "PA",
        "office_type": "State",
        "campaign_year": "2022",
        "_version_": 1737393594126303200,
        "score": 0.24995676
      },
      {
        "id": "17843924-f204-9333-7cf5-9a7774ad0d6e",
        "file_id": "17843924-f204-9333-7cf5-9a7774ad0d6e",
        "file_name": "radio nab Chuck Gray Casper, Rawlins WY 07032022",
        "file_extension": "pdf",
        "file_size": 1104738,
        "file_status": "com_cpy",
        "folder_id": "33ba78f4-d9a6-b46d-ed38-e5cfa7604dc8",
        "create_ts": "2022-07-04T03:43:28.269Z",
        "last_update_ts": "2022-07-04T03:43:45.257Z",
        "active_ind": "Y",
        "file_manager_id": "c12da97c-e730-485b-8745-38be4b71a271",
        "file_folder_path": "Political Files/2022/State",
        "full_qualified_file_name": "Political Files/2022/State/radio nab Chuck Gray Casper, Rawlins WY 07032022",
        "entity_id": "47878",
        "source_service_code": "FM",
        "callsign": "KQLT",
        "political_file_type": "PA",
        "office_type": "State",
        "campaign_year": "2022",
        "_version_": 1737392085035647000,
        "score": 0.24995676
      },
      {
        "id": "b44d42eb-8279-e485-415e-5721921bb0d4",
        "file_id": "b44d42eb-8279-e485-415e-5721921bb0d4",
        "file_name": "radio nab Chuck Gray Casper, Rawlins WY 07032022",
        "file_extension": "pdf",
        "file_size": 1104738,
        "file_status": "com_cpy",
        "folder_id": "330ba30e-e9f0-0a8b-5b86-7d2c1dfae11a",
        "create_ts": "2022-07-04T03:09:19.233Z",
        "last_update_ts": "2022-07-04T03:09:04.569Z",
        "active_ind": "Y",
        "file_manager_id": "3a87643d-cc0b-4b94-b71e-4e4099e1d7d5",
        "file_folder_path": "Political Files/2022/State",
        "full_qualified_file_name": "Political Files/2022/State/radio nab Chuck Gray Casper, Rawlins WY 07032022",
        "entity_id": "15925",
        "source_service_code": "FM",
        "callsign": "KHOC",
        "political_file_type": "PA",
        "office_type": "State",
        "campaign_year": "2022",
        "_version_": 1737389936372351000,
        "score": 0.24995676
      },
      {
        "id": "07b81aac-005c-dbdb-1d23-5950344d6854",
        "file_id": "07b81aac-005c-dbdb-1d23-5950344d6854",
        "file_name": "Lisa Zavogiannis WTRZ (070422)",
        "file_extension": "pdf",
        "file_size": 1790326,
        "file_status": "com_cpy",
        "folder_id": "22fcc1a5-5fd5-b9f5-a3f9-fe089ee5ae76",
        "create_ts": "2022-07-04T02:38:54.065Z",
        "last_update_ts": "2022-07-04T02:39:10.756Z",
        "active_ind": "Y",
        "file_manager_id": "4e7b6088-bada-4424-8732-6a5adfd44129",
        "file_folder_path": "Political Files/2022/Local",
        "full_qualified_file_name": "Political Files/2022/Local/Lisa Zavogiannis WTRZ (070422)",
        "entity_id": "17759",
        "source_service_code": "FM",
        "callsign": "WTRZ",
        "political_file_type": "PA",
        "office_type": "Local",
        "campaign_year": "2022",
        "_version_": 1737388022442229800,
        "score": 0.24995676
      },
      {
        "id": "c4e3fcf6-420b-5435-9e56-456f529d32d0",
        "file_id": "c4e3fcf6-420b-5435-9e56-456f529d32d0",
        "file_name": "Jimmy Haley WTRZ (070422)",
        "file_extension": "pdf",
        "file_size": 1349083,
        "file_status": "com_cpy",
        "folder_id": "22fcc1a5-5fd5-b9f5-a3f9-fe089ee5ae76",
        "create_ts": "2022-07-04T02:38:53.829Z",
        "last_update_ts": "2022-07-04T02:38:39.449Z",
        "active_ind": "Y",
        "file_manager_id": "1d2b673a-922e-4d21-98f4-55bcbdf3b001",
        "file_folder_path": "Political Files/2022/Local",
        "full_qualified_file_name": "Political Files/2022/Local/Jimmy Haley WTRZ (070422)",
        "entity_id": "17759",
        "source_service_code": "FM",
        "callsign": "WTRZ",
        "political_file_type": "PA",
        "office_type": "Local",
        "campaign_year": "2022",
        "_version_": 1737388022574350300,
        "score": 0.24995676
      },
      {
        "id": "fc9c2727-a4c1-8897-b658-a75d621eeee0",
        "file_id": "fc9c2727-a4c1-8897-b658-a75d621eeee0",
        "file_name": "Chris Stanford WTRZ (070222)",
        "file_extension": "pdf",
        "file_size": 1186646,
        "file_status": "com_cpy",
        "folder_id": "22fcc1a5-5fd5-b9f5-a3f9-fe089ee5ae76",
        "create_ts": "2022-07-04T02:38:53.492Z",
        "last_update_ts": "2022-07-04T02:38:39.33Z",
        "active_ind": "Y",
        "file_manager_id": "be278a35-63cb-4451-bc44-18e2be8b7534",
        "file_folder_path": "Political Files/2022/Local",
        "full_qualified_file_name": "Political Files/2022/Local/Chris Stanford WTRZ (070222)",
        "entity_id": "17759",
        "source_service_code": "FM",
        "callsign": "WTRZ",
        "political_file_type": "PA",
        "office_type": "Local",
        "campaign_year": "2022",
        "_version_": 1737388022454812700,
        "score": 0.24995676
      }
    ],
    "facets": {
      "nielsen_dma_rank": {
        "DES MOINES-AMES": 8390,
        "WILKES BARRE-SCRANTON": 7798,
        "LAS VEGAS": 7533,
        "CEDAR RAPIDS-WTRLO-IWC&DUB": 7198,
        "PITTSBURGH": 7157,
        "WEST PALM BEACH-FT. PIERCE": 5830,
        "HONOLULU": 5227,
        "DULUTH-SUPERIOR": 4656,
        "CHARLESTON-HUNTINGTON": 4383,
        "PORTLAND-AUBURN": 4312,
        "TALLAHASSEE-THOMASVILLE": 4169,
        "OMAHA": 4063,
        "RALEIGH-DURHAM (FAYETVLLE)": 3950,
        "BUTTE-BOZEMAN": 3662,
        "PORTLAND OR": 3516,
        "EUGENE": 3512,
        "MISSOULA": 3481,
        "MINNEAPOLIS-ST. PAUL": 3265,
        "CHAMPAIGN&SPRNGFLD-DECATUR": 3247,
        "BEND OR": 3238,
        "SACRAMNTO-STKTON-MODESTO": 3084,
        "CHICAGO": 3058,
        "WAUSAU-RHINELANDER": 2959,
        "FRESNO-VISALIA": 2908,
        "SAVANNAH": 2901,
        "BIRMINGHAM (ANN TUSC)": 2792,
        "QUINCY-HANNIBAL-KEOKUK": 2776,
        "KANSAS CITY": 2770,
        "FT. WAYNE": 2730,
        "MILWAUKEE": 2656,
        "GREENSBORO-H.POINT-W.SALEM": 2560,
        "PEORIA-BLOOMINGTON": 2542,
        "Greenville-Spartanburg-Asheville-Anderson": 2349,
        "PHILADELPHIA": 2326,
        "GRAND RAPIDS-KALMZOO-B.CRK": 2211,
        "ROCKFORD": 2172,
        "TAMPA-ST. PETE (SARASOTA)": 2172,
        "LEXINGTON": 2151,
        "LA CROSSE-EAU CLAIRE": 2143,
        "ROCHESTR-MASON CITY-AUSTIN": 2003,
        "WASHINGTON DC (HAGRSTWN)": 1990,
        "GREAT FALLS": 1941,
        "MADISON": 1939,
        "ALBUQUERQUE-SANTA FE": 1938,
        "BLUEFIELD-BECKLEY-OAK HILL": 1763,
        "SIOUX CITY": 1763,
        "LINCOLN & HASTINGS-KRNY": 1656,
        "PADUCAH-CAPE GIRARD-HARSBG": 1650,
        "BINGHAMTON": 1615,
        "PHOENIX (PRESCOTT)": 1607,
        "GREENVLL-SPART-ASHEVLL-AND": 1562,
        "BURLINGTON-PLATTSBURGH": 1523,
        "FARGO-VALLEY CITY": 1446,
        "LITTLE ROCK-PINE BLUFF": 1443,
        "MINOT-BISMARCK-DICKINSON": 1426,
        "PROVIDENCE-NEW BEDFORD": 1422,
        "GREEN BAY-APPLETON": 1381,
        "CHATTANOOGA": 1380,
        "MIAMI-FT. LAUDERDALE": 1305,
        "ANCHORAGE": 1300,
        "GAINESVILLE": 1268,
        "ST. LOUIS": 1248,
        "JOHNSTOWN-ALTOONA-ST COLGE": 1230,
        "LOS ANGELES": 1219,
        "LOUISVILLE": 1184,
        "WICHITA-HUTCHINSON PLUS": 1148,
        "NEW YORK": 1139,
        "CHARLOTTE": 1112,
        "COLUMBUS OH": 1110,
        "SALT LAKE CITY": 1107,
        "GLENDIVE": 1081,
        "FT. SMITH-FAY-SPRNGDL-RGRS": 1065,
        "DENVER": 1064,
        "ORLANDO-DAYTONA BCH-MELBRN": 1044,
        "JACKSON MS": 1003,
        "DAYTON": 999,
        "OKLAHOMA CITY": 960,
        "DALLAS-FT. WORTH": 926,
        "TULSA": 912,
        "PANAMA CITY": 879,
        "LANSING": 862,
        "INDIANAPOLIS": 841,
        "YOUNGSTOWN": 816,
        "GREENVILLE-N.BERN-WASHNGTN": 804,
        "HELENA": 792,
        "COLORADO SPRINGS-PUEBLO": 772,
        "MACON": 762,
        "TWIN FALLS": 756,
        "AUSTIN": 743,
        "FLINT-SAGINAW-BAY CITY": 731,
        "ATLANTA": 707,
        "BUFFALO": 702,
        "SAN FRANCISCO-OAK-SAN JOSE": 691,
        "BANGOR": 676,
        "HARTFORD & NEW HAVEN": 661,
        "SAN DIEGO": 659,
        "RENO": 657,
        "MONTEREY-SALINAS": 645,
        "EL PASO (LAS CRUCES)": 641,
        "TERRE HAUTE": 641
      },
      "network_affiliation": {
        "ABC": 64372,
        "NBC": 60860,
        "CBS": 42614,
        "FOX": 30585,
        "PBS": 14802,
        "CW": 12411,
        "IND": 3037,
        "MYTV": 2264,
        "UNIVISION": 1907,
        "MY NETWORK": 1682,
        "CBS/NBC": 1081,
        "FAMILYNET": 990,
        "MNT": 945,
        "TELEMUNDO": 931,
        "ION": 890,
        "N/A": 655,
        "CBS/CW": 609,
        "UNIMAS": 606,
        "INDEPENDENT": 430,
        "NBC & CBS": 376,
        "THE CW NETWORK": 325,
        "MYNETWORKTV": 317,
        "ABC, NBC": 236,
        "NONE": 231,
        "ETV": 213,
        "TRINITY BROADCASTING NETWORK": 179,
        "NBC & CW (DIGITAL ONLY)": 162,
        "Independent": 157,
        "MeTV": 136,
        "CBS AND CW": 100,
        "CBS/FOX": 95,
        "NBC/CW": 94,
        "THIS NETWORK LLC": 94,
        "CBS AND FOX": 92,
        "MY NETWORK TV": 74,
        "CW TELEVISION NETWORK": 50,
        "TBN": 46,
        "AZTECA AMERICA": 39,
        "CW/MeTV": 35,
        "MYNETWORK TV": 30,
        "ABC; NBC": 27,
        "MTV TR3S": 27,
        "ABC & CW (DIGITAL ONLY)": 21,
        "AMER1 (CH 44-1); AZTECA AMERICA (CH. 44-2)": 17,
        "PUBLIC BROADCASTING SERVICE": 15,
        "MNT AND CW (DIGITAL ONLY)": 12,
        "Cablevision": 10,
        "RTN": 9,
        "NBC/FOX": 8,
        "TELMUNDO": 8,
        "UNVISION": 8,
        "iON": 6,
        "My Net, MeTV, Movies Network": 4,
        "SBS/MEGA": 4,
        "TBN ENLACE": 4,
        "CW, AMERICA ONE": 3,
        "MYNETWORK": 3,
        "REL": 3,
        "SHOP AT HM": 3,
        "TUVISION": 1
      },
      "campaign_year": {
        "2012": 3181,
        "2013": 384,
        "2014": 22060,
        "2015": 6067,
        "2016": 66094,
        "2017": 10303,
        "2018": 67578,
        "2019": 13895,
        "2020": 124574,
        "2021": 22737,
        "2022": 46949,
        "KYAZ": 5,
        "Fede": 1
      },
      "office_type": {
        "State": 81156,
        "US Senate": 53259,
        "US House": 46658,
        "Presidential": 37948,
        "Local": 28029
      },
      "non_political_file_folder": {
        "Records Concerning Commercial Limits in Childrens Programs": 63687,
        "Issues and Programs Lists": 46383,
        "Equal Employment Opportunity Records": 37662,
        "Donor Lists - Applicable Only for NCEs": 12305,
        "FCC Authorizations": 7478,
        "Local Public Notice Announcements": 1894,
        "Availability of Signals": 1874,
        "Applications and Related Materials": 1718,
        "FCC Investigations or Complaints": 1557,
        "Must-Carry or Retransmission Consent": 1302,
        "Childrens TV Programming Reports": 1161,
        "Ownership Reports": 1114,
        "Class A TV Continuing Eligibility": 656,
        "Political Matters and Controversial Issues Disclosures": 655,
        "State and Local Franchising Related Materials": 503,
        "Time Brokerage Agreements": 454,
        "Channels Delivered": 275,
        "Compatibility with Consumer Electronics Equipment": 148,
        "Information on Third-Party Fundraising - For NCE Stations Only": 84,
        "Auction Transition Consumer Certification": 83,
        "Joint Sales Agreements": 79,
        "Citizen Agreements": 57,
        "Shared Service Agreements": 52,
        "Operator Interests in Video Programming": 33,
        "Sponsorship Identification": 16,
        "Leased Access": 14,
        "Foreign Government-Provided Programming Disclosures": 4,
        "Noncommercial Set-Aside": 1
      },
      "source_service_code": {
        "TV": 257002,
        "CABLE": 132446,
        "FM": 122055,
        "AM": 47088,
        "DBS": 6494
      },
      "political_file_type": {
        "PA": 248657,
        "NCIA": 135179
      }
    }
  },
  "request": {
    "qs": "t=opif&q=page%20offset%200&s=0&o=new",
    "query": {
      "t": "opif",
      "q": "page offset 0",
      "s": "0",
      "o": "new"
    }
  },
  "responseStatus": {
    "status": 200,
    "type": "OK",
    "queryTime": 211,
    "processTime": 221,
    "responseTime": 221
  }
}
